bytedance_creative_tools/__init__.py
bytedance_creative_tools-0.0.1.dist-info/METADATA
bytedance_creative_tools-0.0.1.dist-info/WHEEL
bytedance_creative_tools-0.0.1.dist-info/top_level.txt
bytedance_creative_tools-0.0.1.dist-info/RECORD
